{
  "owners": [
    {
      "id": "owner-maya",
      "name": "Maya Chen",
      "email": "maya@utexas.edu",
      "createdAt": "2026-03-08T19:05:00.000Z",
      "updatedAt": "2026-03-08T19:05:00.000Z"
    },
    {
      "id": "owner-jordan",
      "name": "Jordan Alvarez",
      "email": "jordan@utexas.edu",
      "createdAt": "2026-03-05T18:25:00.000Z",
      "updatedAt": "2026-03-05T18:25:00.000Z"
    },
    {
      "id": "owner-priya",
      "name": "Priya Raman",
      "email": "priya@utexas.edu",
      "createdAt": "2026-02-27T21:12:00.000Z",
      "updatedAt": "2026-02-27T21:12:00.000Z"
    },
    {
      "id": "owner-eb6401cb-1339-4ff9-b584-f928d1d7e344",
      "name": "Johnny",
      "email": "johnnyshen0630@gmail.com",
      "createdAt": "2026-03-11T01:24:05.011Z",
      "updatedAt": "2026-03-11T01:37:37.344Z"
    }
  ],
  "passports": [
    {
      "id": "passport-burnt-commuter",
      "slug": "burnt-commuter",
      "ownerId": "owner-maya",
      "nickname": "Burnt Orange Commuter",
      "make": "Trek",
      "model": "FX 2 Disc",
      "color": "Burnt orange",
      "frameSize": "Medium",
      "serialNumber": "WTU2485MUT26",
      "lockType": "U-lock + braided cable",
      "commonParking": "PCL racks, Speedway Mall, Welch Hall",
      "purchaseDate": "August 2025",
      "purchaseSource": "Bicycle Sport Shop",
      "receiptReference": "Printed receipt uploaded during orientation week.",
      "photoSummary": "Three full-bike shots plus a close-up of the Longhorn bottle cage sticker.",
      "receiptStatus": "Uploaded",
      "status": "Stolen",
      "lastSeen": "March 8, 2026 at 6:20 PM",
      "reportedAt": "March 8, 2026 at 7:05 PM",
      "note": "Bottle cage has a small Longhorn sticker and a hidden QR ownership tag.",
      "heroTone": "burnt",
      "createdAt": "2026-03-08T19:05:00.000Z",
      "updatedAt": "2026-03-08T19:05:00.000Z"
    },
    {
      "id": "passport-midnight-fixie",
      "slug": "midnight-fixie",
      "ownerId": "owner-jordan",
      "nickname": "Midnight Fixie",
      "make": "State Bicycle Co.",
      "model": "4130 Single Speed",
      "color": "Matte black",
      "frameSize": "Large",
      "serialNumber": "SBC4130ATX92",
      "lockType": "Kryptonite New-U lock",
      "commonParking": "Jester racks, Greg Gym, East Campus Garage",
      "purchaseDate": "January 2026",
      "purchaseSource": "Facebook Marketplace",
      "receiptReference": "Bill of sale screenshot saved in account.",
      "photoSummary": "Two side profiles and a drivetrain close-up.",
      "receiptStatus": "Pending",
      "status": "Protected",
      "note": "Front wheel quick release replaced with security skewers.",
      "heroTone": "sage",
      "createdAt": "2026-03-05T18:25:00.000Z",
      "updatedAt": "2026-03-05T18:25:00.000Z"
    },
    {
      "id": "passport-silver-hauler",
      "slug": "silver-hauler",
      "ownerId": "owner-priya",
      "nickname": "Silver Hauler",
      "make": "Specialized",
      "model": "Sirrus X 3.0",
      "color": "Silver mist",
      "frameSize": "Small",
      "serialNumber": "WSBC604ATX18",
      "lockType": "Folding lock",
      "commonParking": "Student Activity Center, GDC, San Antonio Garage",
      "purchaseDate": "June 2024",
      "purchaseSource": "REI",
      "receiptReference": "Digital REI receipt linked in account.",
      "photoSummary": "Full-bike shot, rear rack close-up, and milk-crate mount detail.",
      "receiptStatus": "Uploaded",
      "status": "Recovered",
      "lastSeen": "February 27, 2026 at 3:45 PM",
      "reportedAt": "February 27, 2026 at 4:12 PM",
      "note": "Rear rack and milk-crate mount make this easy to identify.",
      "heroTone": "steel",
      "createdAt": "2026-02-27T21:12:00.000Z",
      "updatedAt": "2026-02-27T21:12:00.000Z"
    },
    {
      "id": "passport-88235d09-ced5-43d6-85c0-714eb7178ede",
      "slug": "lol",
      "ownerId": "owner-eb6401cb-1339-4ff9-b584-f928d1d7e344",
      "nickname": "LOL",
      "make": "LOL",
      "model": "LOL",
      "color": "LOL",
      "frameSize": "LOL",
      "serialNumber": "LOL",
      "lockType": "U-lock",
      "commonParking": "PCL racks",
      "purchaseDate": "LOL",
      "purchaseSource": "LOL",
      "receiptReference": "LOL",
      "photoSummary": "LOL",
      "receiptStatus": "Uploaded",
      "status": "Protected",
      "note": "wjeborgj",
      "heroTone": "burnt",
      "createdAt": "2026-03-11T01:24:05.011Z",
      "updatedAt": "2026-03-11T01:24:05.011Z"
    },
    {
      "id": "passport-f56dfced-7b31-4fc3-8f45-609bdb8f405f",
      "slug": "lol-2",
      "ownerId": "owner-eb6401cb-1339-4ff9-b584-f928d1d7e344",
      "nickname": "lol",
      "make": "lol",
      "model": "lol",
      "color": "lol",
      "frameSize": "lol",
      "serialNumber": "lol",
      "lockType": "U-lock",
      "commonParking": "PCL racks",
      "purchaseDate": "lol",
      "purchaseSource": "lol",
      "receiptReference": "lol",
      "photoSummary": "lol",
      "receiptStatus": "Uploaded",
      "status": "Protected",
      "note": "No distinctive notes yet.",
      "heroTone": "burnt",
      "createdAt": "2026-03-11T01:37:37.344Z",
      "updatedAt": "2026-03-11T01:37:37.344Z"
    }
  ],
  "recoveredBikes": [
    {
      "id": "recovered-101",
      "title": "Recovered commuter bike",
      "foundAt": "March 10, 2026",
      "zone": "San Antonio Garage",
      "holdStatus": "Awaiting owner response",
      "note": "Orange frame, city tires, bottle cage scuff marks.",
      "matchCandidates": [
        {
          "passportSlug": "burnt-commuter",
          "confidence": "High",
          "reason": "Exact color profile, matching rack location history, and matching accessories."
        }
      ],
      "createdAt": "2026-03-10T18:30:00.000Z",
      "updatedAt": "2026-03-10T18:30:00.000Z"
    },
    {
      "id": "recovered-102",
      "title": "Recovered silver hybrid",
      "foundAt": "March 7, 2026",
      "zone": "East Campus perimeter",
      "holdStatus": "Needs owner review",
      "note": "Rear rack installed, silver frame, front light mount missing.",
      "matchCandidates": [
        {
          "passportSlug": "silver-hauler",
          "confidence": "Medium",
          "reason": "Strong visual overlap, but serial number not yet confirmed."
        }
      ],
      "createdAt": "2026-03-07T17:00:00.000Z",
      "updatedAt": "2026-03-07T17:00:00.000Z"
    },
    {
      "id": "recovered-103",
      "title": "Recovered black single-speed",
      "foundAt": "March 5, 2026",
      "zone": "Dobie loading zone",
      "holdStatus": "No clean match yet",
      "note": "Matte black frame with security skewers and flat pedals.",
      "matchCandidates": [
        {
          "passportSlug": "midnight-fixie",
          "confidence": "Needs review",
          "reason": "Wheel setup matches, but the stem and seatpost differ from the uploaded photos."
        }
      ],
      "createdAt": "2026-03-05T15:40:00.000Z",
      "updatedAt": "2026-03-05T15:40:00.000Z"
    }
  ]
}